{
  "loginUsingPOST": {},
  "getUserPresentationListUsingGET": {},
  "createUserUsingPOST": {},
  "getPermissionPresentationListUsingGET": {},
  "createPermissionUsingPOST": {},
  "updatePermissionUsingPUT": {},
  "getPermissionByKeyUsingGET": {
    "permissionKey|path": [
      "default",
      "LOGIN",
      "ADMIN_STATISTICS",
      "ADMIN_USER_DATA",
      "VIEW_PROFILE",
      "vuq",
      "",
      "88DSyxeO",
      "Hze3upWZIBLk",
      "[None]",
      [],
      "HuepgfmdFsMJDma",
      "g",
      "r0IY1GlimmrypjVJ3NZo",
      "lGScugLolD",
      "z1H",
      "UFFa",
      "TxF",
      "Vt",
      "Mdi",
      "ryxvHid",
      "TnofZ06GuMdRp",
      "kEe",
      "TH",
      "Z",
      "ytLC8YQg9ZSYVwEhi6",
      "0upe4zI6Xv9R0cdBH",
      "7m8ah",
      "T",
      "[-2889, -2493, -8682, -7531]",
      "3l",
      "nyxt3",
      "F",
      "jcoaL",
      "4",
      "95",
      true,
      "bZd",
      "55",
      "aq0MS",
      "qo2be2DHSeF4A3B",
      "Ct6lfdW1Eb9xzw1oJ",
      "hlR",
      "s9j",
      "35",
      "X7B3gt",
      "6",
      "54",
      "209",
      "137",
      "11",
      "26",
      "kf",
      "True",
      "24",
      "GbElyS",
      "96",
      "xsmvDPloylPLw8tILc",
      "94",
      "M0EoJTf5",
      "139",
      "16",
      "104",
      "236",
      "L",
      "7",
      "3vAa8Du",
      "13",
      "o1AW5Nhu2hSLp0rwJCj4r66VaIKyQYZ2vvzNS",
      "bXl",
      "118",
      "mWXZXH4d",
      "29",
      "58",
      "57",
      "82",
      "85",
      "4bLolhmL1",
      "81",
      "G6TmH",
      "i2GD3Ef",
      "164",
      "173",
      "h8g8",
      "pN",
      "231",
      "0",
      "73",
      "zRTm0uLgAHtf",
      275,
      "275",
      "1u4pkg",
      "n",
      "WUDbKGqe",
      "62",
      "258",
      "194",
      "4N89ZtnW",
      "100",
      "fyh8CmC357qeRfEhFHtNKKPhYrkIFn56td9ZzcexD8EN0",
      "40",
      "190",
      "105",
      "p9S",
      "183",
      "261",
      "70",
      "T0QqwTFPWljPV0",
      "20",
      "299",
      "143",
      "uljay",
      "HXgSJ76IOdXv",
      "250",
      "y9vOJOxqAqLebwPw5ImtGWVV7nptZ",
      "8LpktB",
      "265",
      20,
      63,
      "39",
      "280",
      "230",
      "83",
      "hJVXK",
      "239",
      6,
      "YuK8KTO0",
      106,
      "122",
      "8",
      "341",
      "215",
      "103",
      "117",
      "hSSWPHM",
      "G",
      "76",
      "V66e6",
      "iu1y",
      "316",
      "M7Tf4eh",
      "E1XdDg",
      "5",
      "9qW0q",
      "315",
      "126",
      "48",
      "MzUrtgWwZKnjFe3q4pE",
      "WBgJsG",
      "458",
      "byPRK",
      "438",
      "hubVrjmRKcdghP",
      "91",
      "1",
      "12",
      "Sw",
      "oarRNdUAnrF",
      "211",
      "300",
      "68",
      "tPhQ",
      "4Y",
      "P7jzsu",
      "339",
      "363",
      "PfyYX8W28W75",
      "qHu",
      "3TXr",
      "2",
      "tY",
      "331",
      "TAkw4uk",
      "raC1drJQiFdhfLDs5fgDbyDJYhVQqsEX5r",
      "249",
      "417",
      "527",
      "399",
      "Zp406",
      "664",
      "335",
      "Fm1s",
      "d",
      "DOXCG",
      "72",
      "208",
      "Hxq",
      "30",
      "i5UdAnZ9J0Go75cb9kbE",
      "LtIYjECOjzxCzsGqD0DOX51ZDeRSBwGu8RnPTD",
      "221",
      "354",
      "502",
      "463",
      "225",
      "mmGUGfrG8jgVvGMW4uJzc8sXRZmW2FEmoyplNKKwAnriDEyQp",
      "380",
      "JMKT8sSnM",
      "q5YXk730NRvTfnRaiYRq",
      "84",
      "S",
      "422",
      "89",
      104,
      "464",
      "253",
      "K",
      "rERNq3ZlUVPf1S",
      "360",
      "456",
      "R6C9",
      "387",
      "shYZMFONRhpTI",
      "267",
      "317",
      "638",
      "s",
      "uBX5M",
      "CbxDx",
      "396",
      "379",
      "86XCPA",
      "Nm7ALtcy",
      "192",
      "389",
      8,
      "172",
      "533",
      "531",
      "wVzM",
      "%s%s%s",
      "302",
      "643",
      "508",
      "257",
      "UWvinr0ILUU",
      "465",
      "sdNq9UV4dOZM7TgYNl",
      "wb8pLCsymOyJ0gnDfedp",
      "326",
      "fRSgCSBn",
      "PdzIRr",
      "515",
      "LcsND",
      "229",
      "279",
      "142",
      "222",
      "420",
      "242",
      "511",
      "u",
      "468",
      "604",
      "f",
      "865",
      240,
      "455",
      "309",
      "0oi3PijagjH9Wurau3x",
      "y18a3Skq4zCzzsnKl6I",
      "63",
      "514",
      "SSN",
      "4sOpOSJSQJwe",
      "90",
      "259",
      "930",
      "aJ7RB9Jwx7rMen5G",
      "Jx8UfynP",
      "JQ",
      "80",
      "{{",
      "521",
      "580",
      "JvQeddK5OR",
      "542",
      "18",
      "1Da",
      "1053",
      "347",
      "312",
      "x",
      "398",
      "403",
      "5xi",
      "725",
      "754",
      "266",
      "92",
      "nhz",
      "320",
      "601",
      "624",
      "S1lfbm",
      "r",
      " ",
      "2026-06-18T19:14:32.05",
      "1060",
      "2026-06-18T19:14:00.772",
      "897",
      "KuZpE2GJvJfoM7zDM1zI5zVpPYmzu",
      "Ddmy85c8vY",
      "2026-06-18T19:13:29.281",
      "498",
      "2026-06-18T19:09:35.528",
      "2026-06-18T19:16:57.962",
      "474",
      "2026-06-18T19:09:30.487",
      "677",
      "614",
      "849",
      "OvO71qBHcpaH2Gu",
      "KZNPro",
      "753",
      "2026-06-18T19:23:34.945",
      "1076",
      13,
      "1217",
      "h",
      "550",
      "452",
      "805",
      "500",
      "885",
      "243",
      "844",
      "2026-06-18T19:09:52.954",
      "890",
      "2026-06-18T19:19:25.892",
      357,
      "79",
      "722",
      "xiyjM4V5b6Zx5vJij",
      "1056",
      "516",
      "2026-06-18T19:24:19.476",
      516,
      "121",
      "306",
      "2026-06-18T19:15:50.667",
      "400",
      "847",
      "409",
      "2026-06-18T19:26:06.84",
      "2026-06-18T19:11:03.409",
      "2026-06-18T19:09:53.659",
      "4.390204385771792",
      "227",
      "17",
      "1081",
      "3",
      "jppnOtJgGPW",
      194,
      "756",
      382,
      "undefined",
      "1hhFdbBPO",
      "882",
      "50",
      "c6yHQ"
    ]
  },
  "deletePermissionByKeyUsingDELETE": {
    "permissionKey|path": [
      "default",
      "ADMIN_STATISTICS",
      "88DSyxeO",
      "vuq",
      "3l",
      "iCftLv3I1oxBdj8lSBJl",
      "5",
      "HuepgfmdFsMJDma",
      "SZTOMqvlZ9IPnVk6QmFgMY6syc8",
      "LOGIN",
      "1ioVv",
      "TxF",
      "g",
      "TH",
      "Hze3upWZIBLk",
      "4bLolhmL1",
      "y9vOJOxqAqLebwPw5ImtGWVV7nptZ",
      "r0IY1GlimmrypjVJ3NZo",
      "kEe",
      "ytLC8YQg9ZSYVwEhi6",
      "zaZjiTjl",
      "z1H",
      "4Y",
      "ryxvHid",
      "lGScugLolD",
      "aq0MS",
      "Vt",
      "0upe4zI6Xv9R0cdBH",
      "hlR",
      "nyxt3",
      "qo2be2DHSeF4A3B",
      "M0EoJTf5",
      "Mdi",
      "ceX3ErbvZYb",
      "p9S",
      "Z",
      "mWXZXH4d",
      "lPx",
      "3vAa8Du",
      "bZd",
      "CbxDx",
      "hubVrjmRKcdghP",
      "shYZMFONRhpTI",
      "rhMsh4qwEmGy6Z",
      "o1AW5Nhu2hSLp0rwJCj4r66VaIKyQYZ2vvzNS",
      "kf",
      "JMOjWnVz",
      "pN",
      [],
      "DG",
      "7m8ah",
      "jcoaL",
      61,
      "GFBEim",
      "fyh8CmC357qeRfEhFHtNKKPhYrkIFn56td9ZzcexD8EN0",
      55,
      29,
      "VGpQW",
      "GbElyS",
      120,
      93,
      "[-2889, -2493, -8682, -7531]",
      81,
      9,
      "Mario",
      105,
      "1u4pkg",
      125,
      2,
      122,
      26,
      104,
      "s9j",
      72,
      80,
      "HXgSJ76IOdXv",
      "X7B3gt",
      206,
      35,
      "gkZ50r4w",
      196,
      100,
      "XoiGs",
      126,
      161,
      180,
      18,
      5,
      "LOpnO0U1iXx0VztN0UvpE0r92",
      94,
      "VIEW_PROFILE",
      24,
      20,
      222,
      68,
      85,
      50,
      53,
      13,
      230,
      197,
      195,
      75,
      "8xPGKirbgd",
      158,
      "q5YXk730NRvTfnRaiYRq",
      83,
      "Fm1s",
      "bXl",
      275,
      "xsmvDPloylPLw8tILc",
      "WUDbKGqe",
      "Ct6lfdW1Eb9xzw1oJ",
      367,
      "true",
      "i2GD3Ef",
      39,
      194,
      326,
      183,
      96,
      299,
      284,
      "r",
      261,
      306,
      14,
      137,
      "7",
      291,
      "vl603",
      360,
      231,
      "uQgUBm",
      25,
      352,
      "258",
      139,
      "T1pQ",
      89,
      63,
      11,
      "zElifrbJ4Dh0RSDNYaN4u0H3InbAa",
      8,
      140,
      280,
      250,
      "T0QqwTFPWljPV0",
      325,
      281,
      102,
      "x",
      "L4iA",
      268,
      69,
      134,
      218,
      490,
      "n",
      95,
      true,
      209,
      "dwMg7Q",
      "6nNbaJS8",
      "wxmFMJ9Pp6veug8OWmG6",
      315,
      "AZAsFE58oU51qMerT",
      434,
      "H9dOE",
      214,
      45,
      "tGSSOgm8",
      "HNkcbR8zQL",
      511,
      "9qW0q",
      82,
      "puOm",
      "b",
      115,
      106,
      482,
      329,
      341,
      438,
      "TYWLJ",
      397,
      76,
      351,
      "iugtsY3QfWD",
      160,
      "mfLZZUFHRwTg9Y5MAj2",
      "OvO71qBHcpaH2Gu",
      173,
      "hdBpMCLfrBtIn4C",
      248,
      "tJ",
      "6KimU",
      "Zp406",
      363,
      103,
      78,
      "lAOZc",
      "Paul",
      237,
      "3CS",
      "byPRK",
      92,
      "P4CbX",
      290,
      "D",
      567,
      "dzkPxwxfpGoR9",
      346,
      508,
      331,
      "509",
      "HQlhAE",
      658,
      210,
      660,
      215,
      702,
      211,
      743,
      "M7Tf4eh",
      308,
      "35",
      "FbAWYi0ts9vf1",
      30,
      "AM",
      "ax4sx",
      "OPdXhL5V02HhtlitqsGd1LZmAJivN6vt8JUV857NXlJJs",
      "agLjbgk",
      464,
      "Sw",
      "zds5lWMdefJ",
      458,
      "rQmTiWIh8MB2yP8Fme55MwJVjR4oU",
      526,
      3,
      0,
      343,
      225,
      "nhz",
      685,
      79,
      "4W",
      "PryhJu4hqi",
      217,
      "hJVXK",
      "P7jzsu",
      "U",
      "EW8166",
      328,
      426,
      91,
      "fnv",
      337,
      "U46O4b0N",
      "YuK8KTO0",
      391,
      499,
      468,
      "C1fWKWSMH9lVscmNa",
      221,
      463,
      "sdNq9UV4dOZM7TgYNl",
      "raC1drJQiFdhfLDs5fgDbyDJYhVQqsEX5r",
      369,
      372,
      145,
      "MzUrtgWwZKnjFe3q4pE",
      "qHu",
      542,
      406,
      164,
      "oarRNdUAnrF",
      "PdzIRr",
      "erL4YG",
      389,
      473,
      314,
      433,
      "h8g8",
      "xF042C6",
      400,
      531,
      "58",
      "R6C9",
      "PMBOv",
      "vYBYKdw",
      302,
      265,
      "5xi",
      480,
      "rkwbjDkOaF3jM0caR",
      851,
      317,
      257,
      732,
      172,
      "KRgYqDfPwMxI5E7avhCJ",
      533,
      "i2E",
      "urM",
      "e",
      697,
      334,
      "jzW",
      242,
      109,
      516,
      "y18a3Skq4zCzzsnKl6I",
      236,
      850,
      368,
      "R3tAmdp",
      174,
      "LcsND",
      143,
      40,
      "ip3Xh",
      304,
      7,
      "GSjHks",
      880,
      501,
      753,
      425,
      62,
      505,
      240,
      600,
      "Jx8UfynP",
      "kjlCHJN5Dpr",
      202,
      "35xucCP4",
      456,
      638,
      407,
      564,
      208,
      259,
      "NNAWq",
      455,
      604,
      470,
      "uljay",
      905,
      809,
      688,
      262,
      605,
      1007,
      644,
      429,
      "55",
      1033,
      "mlfqv1",
      366,
      865,
      "kCW9c66IEDqx3OuHF00XrsL",
      "86XCPA",
      "pFeN2n9",
      568,
      432,
      1006,
      300,
      "4iuA",
      "YLcLv3F",
      "iu1y",
      266,
      "Ns3WVviM3AymwwddhsoLcm4RbzUp",
      335,
      "rERNq3ZlUVPf1S",
      388,
      "JQ",
      "2026-06-18T19:09:53.659",
      "vXWX1LWyQB90dtMqy6nXr9",
      184,
      457,
      942,
      "uBX5M",
      "2eCDXZte5FnKoC9pB4t",
      720,
      1024,
      "aJ7RB9Jwx7rMen5G",
      555,
      949,
      123,
      "V66e6",
      813,
      522,
      834,
      409,
      "S",
      420,
      442,
      "2026-06-18T19:09:28.074",
      "8LpktB",
      628,
      "WBgJsG",
      404,
      1188,
      66,
      "L",
      941,
      "DaXZKjNnVaRT",
      "JMKT8sSnM",
      "TySN62bd",
      "81",
      "1243",
      "fRSgCSBn",
      538,
      619,
      "KZNPro",
      959,
      "2ZDsr",
      601,
      1262,
      279,
      178,
      297,
      "vbxij5",
      852,
      267,
      1288,
      805,
      401,
      "130",
      1046,
      569,
      924,
      1042,
      1124,
      12,
      974,
      "SnHDl",
      485,
      609,
      1244,
      518,
      "bt7NLbR91",
      6,
      1190,
      57,
      436,
      1064,
      "rLT",
      973,
      532,
      1074,
      "0oi3PijagjH9Wurau3x",
      "FxbYpT",
      1253,
      413,
      687
    ]
  },
  "getRolePresentationListUsingGET": {},
  "createRoleUsingPOST": {},
  "getRoleByIdUsingGET": {
    "roleId|path": [
      1,
      10,
      5,
      2,
      8,
      18,
      9,
      6,
      19,
      7,
      21,
      24,
      20,
      23,
      26,
      27,
      32,
      30,
      16,
      28,
      3,
      13,
      4,
      33,
      40,
      29,
      25,
      37,
      17,
      45,
      41,
      46,
      44,
      34,
      48,
      42,
      43,
      38,
      53,
      58,
      60,
      66,
      47,
      49,
      64,
      36,
      68,
      73,
      35,
      70,
      59,
      77,
      31,
      61,
      82,
      93,
      55,
      62,
      81,
      86,
      83,
      67,
      101,
      89,
      76,
      78,
      79,
      90,
      111,
      107,
      110,
      50,
      112,
      91,
      106,
      125,
      123,
      74,
      113,
      87,
      131,
      122,
      118,
      132,
      114,
      143,
      129,
      103,
      135,
      117,
      140,
      96,
      128,
      69,
      115,
      134,
      149,
      108,
      52,
      139,
      142,
      138,
      109,
      121,
      92,
      137,
      157,
      57,
      105,
      54,
      133,
      124,
      153,
      172,
      173,
      144,
      147,
      51,
      104,
      183,
      184,
      190,
      127,
      199,
      158,
      155,
      210,
      95,
      194,
      192,
      130,
      65,
      212,
      187,
      221,
      163,
      180,
      176,
      217,
      169,
      100,
      170,
      152,
      223,
      175,
      213,
      168,
      204,
      191,
      84,
      248,
      200,
      211,
      119,
      236,
      188,
      162,
      177,
      258,
      233,
      165,
      247,
      264,
      238,
      269,
      225,
      206,
      254,
      39,
      220,
      250,
      209,
      255,
      202,
      230,
      198,
      272,
      256,
      235,
      181,
      265,
      174,
      279,
      296,
      234,
      239,
      193,
      222,
      268,
      295,
      298,
      186,
      285,
      242,
      171,
      189,
      179,
      229,
      146,
      197,
      214,
      305,
      323,
      263,
      145,
      332,
      334,
      228,
      326,
      207,
      201,
      260,
      278,
      327,
      315,
      275,
      232,
      333,
      313,
      307,
      150,
      237,
      276,
      218,
      277,
      300,
      282,
      330,
      249,
      72,
      284,
      245,
      322,
      344,
      347,
      270,
      299,
      "39",
      283,
      224,
      148,
      294,
      352,
      309,
      363,
      195,
      246,
      351,
      360,
      215,
      377,
      336,
      362,
      342,
      335,
      273,
      267,
      345,
      161,
      185,
      366,
      226,
      388,
      182,
      231,
      348,
      381,
      403,
      219,
      406,
      339,
      216,
      308,
      380,
      399,
      310,
      376,
      343,
      356,
      312,
      385,
      402,
      412,
      415,
      382,
      428,
      329,
      434,
      391,
      424,
      432,
      167,
      372,
      396,
      205,
      442,
      387,
      243,
      400,
      350,
      447,
      445,
      404,
      156,
      451,
      459,
      361,
      413,
      438,
      462,
      301,
      317,
      368,
      441,
      383,
      417,
      390,
      411,
      303,
      423,
      454,
      449,
      479,
      470,
      321,
      364,
      487,
      489,
      304,
      178,
      497,
      151,
      505,
      427,
      439,
      425,
      353,
      503,
      468,
      482,
      478,
      473,
      522,
      203,
      500,
      397,
      460,
      287,
      302,
      481,
      525,
      528,
      355,
      543,
      464,
      259,
      "367",
      419,
      532,
      494,
      271,
      410,
      547,
      498,
      414,
      488,
      420,
      448,
      514,
      499,
      554,
      384,
      504,
      574,
      290,
      251,
      461,
      581,
      359,
      252,
      367,
      436,
      587,
      548,
      444,
      594,
      582,
      241,
      530,
      601
    ]
  },
  "deleteRoleByIdUsingDELETE": {
    "roleId|path": [
      11,
      1,
      10,
      5,
      9,
      15,
      12,
      2,
      19,
      18,
      14,
      22,
      16,
      20,
      33,
      8,
      13,
      3,
      29,
      44,
      41,
      28,
      17,
      45,
      37,
      24,
      25,
      21,
      4,
      42,
      53,
      6,
      32,
      26,
      34,
      23,
      30,
      35,
      27,
      7,
      46,
      47,
      49,
      60,
      48,
      88,
      40,
      38,
      97,
      56,
      82,
      94,
      83,
      66,
      80,
      101,
      71,
      59,
      70,
      99,
      58,
      63,
      85,
      "102",
      64,
      74,
      114,
      120,
      77,
      90,
      103,
      91,
      75,
      122,
      67,
      87,
      68,
      116,
      79,
      98,
      154,
      129,
      142,
      132,
      141,
      113,
      62,
      157,
      137,
      143,
      109,
      43,
      138,
      76,
      106,
      92,
      112,
      55,
      81,
      134,
      128,
      131,
      125,
      93,
      135,
      54,
      184,
      190,
      199,
      57,
      173,
      117,
      149,
      210,
      51,
      126,
      155,
      110,
      172,
      86,
      217,
      73,
      31,
      130,
      108,
      176,
      180,
      118,
      65,
      89,
      221,
      152,
      187,
      183,
      153,
      194,
      191,
      175,
      119,
      170,
      84,
      248,
      258,
      164,
      212,
      169,
      165,
      223,
      177,
      121,
      266,
      95,
      160,
      204,
      236,
      188,
      36,
      209,
      127,
      234,
      78,
      288,
      211,
      296,
      225,
      174,
      104,
      298,
      235,
      115,
      202,
      162,
      324,
      325,
      268,
      269,
      171,
      311,
      253,
      192,
      331,
      265,
      179,
      333,
      197,
      247,
      145,
      318,
      306,
      186,
      213,
      181,
      263,
      111,
      146,
      237,
      326,
      344,
      218,
      200,
      239,
      323,
      220,
      322,
      313,
      238,
      276,
      168,
      250,
      195,
      307,
      284,
      363,
      281,
      201,
      327,
      39,
      357,
      270,
      345,
      246,
      295,
      255,
      249,
      388,
      136,
      275,
      230,
      349,
      214,
      207,
      231,
      334,
      395,
      381,
      315,
      278,
      267,
      409,
      "215",
      240,
      224,
      264,
      226,
      362,
      310,
      189,
      407,
      206,
      418,
      393,
      401,
      147,
      366,
      299,
      377,
      219,
      227,
      185,
      399,
      437,
      107,
      403,
      260,
      400,
      379,
      305,
      277,
      228,
      438,
      161,
      193,
      370,
      435,
      301,
      139,
      390,
      463,
      372,
      96,
      445,
      282,
      382,
      396,
      309,
      123,
      350,
      "391",
      434,
      449,
      144,
      385,
      216,
      489,
      232,
      425,
      "389",
      470,
      474,
      439,
      285,
      431,
      505,
      478,
      365,
      156,
      520,
      297,
      430,
      477,
      397,
      383,
      314,
      465,
      373,
      339,
      443,
      440,
      493,
      205,
      502,
      358,
      348,
      353,
      526,
      482,
      506,
      340,
      405,
      356,
      272,
      516,
      564,
      466,
      330,
      50,
      498,
      519,
      468,
      380,
      178,
      518,
      328,
      291,
      552,
      140,
      522,
      387,
      539,
      354,
      584,
      541,
      472,
      501,
      417,
      480,
      515,
      514,
      481,
      583,
      321,
      521,
      483,
      411,
      289,
      602,
      279
    ]
  },
  "addPermissionOnRoleUsingPOST": {
    "permissionKey|path": [
      "default",
      "VIEW_PROFILE",
      "88DSyxeO",
      "vuq",
      "ADMIN_STATISTICS",
      "Hze3upWZIBLk",
      "LOGIN",
      [],
      "TH",
      "ADMIN_USER_DATA",
      "UFFa",
      "y9vOJOxqAqLebwPw5ImtGWVV7nptZ",
      "g",
      "HuepgfmdFsMJDma",
      "lGScugLolD",
      "r0IY1GlimmrypjVJ3NZo",
      "[None]",
      [
        -2889,
        -2493,
        -8682,
        -7531
      ],
      "[-2889, -2493, -8682, -7531]",
      "TnofZ06GuMdRp",
      0,
      "0",
      4,
      "Z",
      "bZd",
      "4",
      "aq0MS",
      "T",
      true,
      "SZTOMqvlZ9IPnVk6QmFgMY6syc8",
      "XoiGs",
      "76",
      "GbElyS",
      "kf",
      "mWXZXH4d",
      "1u4pkg",
      55,
      "7m8ah",
      "3vAa8Du",
      "z1H",
      "4bLolhmL1",
      20,
      13,
      230,
      81,
      "0upe4zI6Xv9R0cdBH",
      100,
      "s9j",
      2,
      "ytLC8YQg9ZSYVwEhi6",
      "ryxvHid",
      "Vt",
      "M0EoJTf5",
      "57",
      "258",
      "bXl",
      "54",
      "81",
      "55",
      "7",
      "100",
      275,
      "jcoaL",
      "PMBOv",
      "190",
      "143",
      "zRTm0uLgAHtf",
      "73",
      "24",
      "HXgSJ76IOdXv",
      "183",
      "104",
      "L",
      "3l",
      "194",
      "F",
      "X7B3gt",
      "62",
      "35",
      "xsmvDPloylPLw8tILc",
      "13",
      63,
      "117",
      "4N89ZtnW",
      "94",
      "kEe",
      "16",
      "164",
      "WUDbKGqe",
      "85",
      "103",
      "fA5EGsJ1y",
      "215",
      "48",
      "26",
      "G",
      "T0QqwTFPWljPV0",
      "96",
      "316",
      "95",
      "TxF",
      "6",
      "i2GD3Ef",
      "399",
      "417",
      "Mdi",
      "3TXr",
      "122",
      "hSSWPHM",
      "Zp406",
      410,
      "137",
      250,
      "fyh8CmC357qeRfEhFHtNKKPhYrkIFn56td9ZzcexD8EN0",
      "70",
      "82",
      "2026-06-18T19:13:29.281",
      "249",
      "20",
      492,
      "331",
      8,
      "%s%s%s",
      "AZAsFE58oU51qMerT",
      "G6TmH",
      "239",
      "mfLZZUFHRwTg9Y5MAj2",
      "iu1y",
      "17",
      "TYWLJ",
      "29",
      "309",
      "E1XdDg",
      "339",
      "79",
      253,
      "387",
      "ceX3ErbvZYb",
      "218",
      "243",
      "Sw",
      "248",
      "396",
      "Ct6lfdW1Eb9xzw1oJ",
      "K",
      "mmGUGfrG8jgVvGMW4uJzc8sXRZmW2FEmoyplNKKwAnriDEyQp",
      232,
      " ",
      436,
      311,
      577,
      890,
      90,
      272,
      793,
      847,
      769,
      326,
      368,
      126,
      292,
      82,
      223,
      11,
      787,
      549,
      459,
      606,
      675,
      682,
      730,
      341,
      48,
      83,
      822,
      694,
      469,
      384,
      844,
      514,
      897,
      "379",
      398,
      663,
      75,
      184,
      473,
      424,
      485,
      "wiEVz",
      621,
      353,
      349,
      859,
      841,
      72,
      84,
      227,
      297,
      458,
      331,
      213,
      243,
      "{{",
      743,
      824,
      "FbAWYi0ts9vf1",
      1043,
      714,
      499,
      930,
      498,
      348,
      "2026-06-18T19:12:31.029",
      717,
      "502",
      465,
      884,
      221,
      401,
      746,
      96,
      1053,
      486,
      978,
      987,
      389,
      324,
      158,
      729,
      590,
      197,
      11.118957857240426,
      1076,
      334,
      1008,
      4.390204385771792,
      1009,
      722,
      1055,
      395,
      91,
      901,
      474,
      "501",
      259,
      1007,
      882,
      879,
      437,
      239,
      468,
      875,
      426,
      425,
      1031,
      1022,
      646,
      264,
      "\"pkbMZ\"",
      173,
      768,
      452,
      376,
      [
        -7147,
        9295,
        7443,
        8941,
        9042,
        1228,
        7727,
        4094,
        -5605,
        8146,
        5517,
        1191
      ],
      6,
      487,
      550,
      755,
      194,
      805,
      "63",
      1116,
      "346",
      419,
      1137,
      887,
      721,
      1065,
      "f",
      "352",
      "638",
      1250,
      517,
      78,
      629,
      780,
      40,
      969,
      1217,
      53,
      1258,
      1209,
      1006,
      800,
      1313,
      409,
      1377,
      773,
      1296,
      886,
      1341,
      700,
      370,
      196,
      928,
      306,
      357,
      145,
      1364,
      303,
      1128,
      402,
      953,
      300,
      235,
      317,
      453,
      257,
      1016,
      877,
      997,
      1023,
      1067,
      30,
      "xiyjM4V5b6Zx5vJij",
      628,
      802,
      1288,
      1052,
      792,
      "334",
      "undefined",
      1075,
      585,
      865,
      451,
      18,
      466,
      440,
      1340,
      638,
      873,
      137,
      1155
    ],
    "roleId|path": [
      1,
      2,
      10,
      5,
      9,
      8,
      13,
      16,
      3,
      22,
      25,
      30,
      23,
      21,
      26,
      29,
      46,
      27,
      24,
      4,
      28,
      37,
      6,
      34,
      40,
      53,
      32,
      7,
      42,
      38,
      49,
      58,
      35,
      47,
      64,
      48,
      77,
      60,
      70,
      66,
      61,
      88,
      94,
      83,
      71,
      82,
      97,
      101,
      80,
      56,
      99,
      50,
      91,
      90,
      59,
      98,
      85,
      63,
      74,
      114,
      115,
      103,
      75,
      120,
      68,
      141,
      87,
      78,
      122,
      116,
      79,
      104,
      129,
      154,
      73,
      131,
      112,
      52,
      107,
      118,
      128,
      123,
      109,
      111,
      89,
      54,
      55,
      81,
      139,
      108,
      31,
      93,
      153,
      133,
      184,
      149,
      183,
      69,
      147,
      158,
      86,
      130,
      124,
      127,
      105,
      152,
      221,
      144,
      194,
      140,
      163,
      248,
      211,
      36,
      236,
      233,
      162,
      213,
      169,
      188,
      95,
      100,
      192,
      96,
      254,
      200,
      265,
      235,
      247,
      230,
      "96",
      242,
      238,
      220,
      198,
      39,
      307,
      320,
      239,
      214,
      206,
      189,
      276,
      321,
      299,
      168,
      327,
      241,
      285,
      295,
      255,
      377,
      264,
      275,
      270,
      387,
      219,
      372,
      222,
      229,
      342,
      345,
      354,
      240,
      315,
      378,
      279,
      261,
      244,
      159,
      259,
      384,
      271,
      404,
      167,
      227,
      287,
      368,
      386,
      376,
      358,
      "272",
      182,
      340,
      356,
      373,
      256,
      161,
      297,
      336,
      341,
      300,
      360,
      419,
      302,
      156,
      332,
      203,
      432,
      403,
      283,
      "398",
      406,
      150,
      359,
      361,
      228,
      410,
      375,
      444,
      423,
      380,
      433,
      330,
      193,
      391,
      317,
      252,
      434,
      420,
      205,
      392,
      274,
      348,
      385,
      291,
      427,
      351,
      273,
      411,
      424,
      447,
      439,
      396,
      445,
      425,
      440,
      328,
      429,
      465,
      319,
      482,
      452,
      472,
      416,
      504,
      451,
      464,
      352,
      478,
      502,
      441,
      436,
      448,
      498,
      474,
      413,
      513,
      347,
      456,
      316,
      343,
      450,
      329,
      148,
      243,
      491,
      422,
      151,
      511,
      507,
      527,
      506,
      442,
      446,
      312,
      337,
      414,
      292,
      178,
      355,
      308,
      335,
      303,
      428,
      494,
      537,
      488,
      517,
      546,
      497,
      515,
      "426",
      453,
      574,
      553,
      467,
      421,
      458,
      590,
      476,
      483,
      503,
      530,
      374,
      604
    ]
  },
  "removePermissionOnRoleUsingDELETE": {
    "permissionKey|path": [
      "LOGIN",
      "ADMIN_USER_DATA",
      "default",
      "VIEW_PROFILE",
      "88DSyxeO",
      "Hze3upWZIBLk",
      "vuq",
      "ADMIN_STATISTICS",
      "[None]",
      "TH",
      "g",
      "TxF",
      "lGScugLolD",
      "HuepgfmdFsMJDma",
      "r0IY1GlimmrypjVJ3NZo",
      "z1H",
      "UFFa",
      "hlR",
      "F",
      "0upe4zI6Xv9R0cdBH",
      "y9vOJOxqAqLebwPw5ImtGWVV7nptZ",
      "[-2889, -2493, -8682, -7531]",
      "p9S",
      [],
      "3l",
      "nyxt3",
      "Mdi",
      "T",
      "TnofZ06GuMdRp",
      "aq0MS",
      "True",
      "s9j",
      "Ct6lfdW1Eb9xzw1oJ",
      "54",
      "kf",
      "ryxvHid",
      "4",
      "5",
      "29",
      "jcoaL",
      "i2GD3Ef",
      "82",
      "zRTm0uLgAHtf",
      "73",
      "96",
      "ytLC8YQg9ZSYVwEhi6",
      "190",
      "4bLolhmL1",
      "35",
      "173",
      "mWXZXH4d",
      "0",
      "24",
      "3vAa8Du",
      "230",
      "81",
      "143",
      "55",
      "xsmvDPloylPLw8tILc",
      "100",
      "275",
      "13",
      "WUDbKGqe",
      "L",
      "76",
      "105",
      "GbElyS",
      "95",
      "4N89ZtnW",
      "85",
      "7",
      "kEe",
      "fyh8CmC357qeRfEhFHtNKKPhYrkIFn56td9ZzcexD8EN0",
      "Z",
      "mfLZZUFHRwTg9Y5MAj2",
      "Zp406",
      "16",
      "fA5EGsJ1y",
      "250",
      "508",
      "503",
      "368",
      "117",
      "1u4pkg",
      "hSSWPHM",
      "iu1y",
      "387",
      "70",
      "62",
      "104",
      "847",
      "LOpnO0U1iXx0VztN0UvpE0r92",
      "wiEVz",
      "57",
      "erL4YG",
      "424",
      "84",
      "239",
      "514",
      "253",
      "8",
      "675",
      "1076",
      "80",
      "391",
      "137",
      "248",
      "769",
      "722",
      "682",
      "26",
      "1007",
      "91",
      "17",
      "2026-06-18T19:18:07.776",
      "459",
      "800",
      "316",
      "886",
      "755",
      "897",
      "5xi",
      "398",
      "63",
      "ceX3ErbvZYb",
      "1022",
      "bZd"
    ],
    "roleId|path": [
      1,
      11,
      10,
      5,
      8,
      9,
      2,
      16,
      13,
      18,
      22,
      20,
      3,
      37,
      33,
      25,
      7,
      41,
      29,
      44,
      4,
      17,
      45,
      6,
      21,
      32,
      24,
      38,
      23,
      40,
      30,
      27,
      46,
      48,
      61,
      70,
      66,
      83,
      90,
      91,
      77,
      64,
      74,
      114,
      115,
      98,
      79,
      75,
      78,
      104,
      73,
      112,
      43,
      154,
      50,
      131,
      52,
      111,
      139,
      133,
      86,
      183,
      118,
      171,
      69,
      163,
      121,
      107,
      124,
      213,
      140,
      158,
      144,
      223,
      236,
      165,
      238,
      123,
      209,
      36,
      192,
      225,
      168,
      254,
      162,
      100,
      285,
      220,
      147,
      189,
      233,
      239,
      272,
      193,
      201,
      275,
      276,
      105,
      146,
      222,
      327,
      229,
      295,
      249,
      242,
      255,
      299,
      150,
      282,
      309,
      260,
      278,
      305,
      279,
      207,
      310,
      336,
      256,
      161,
      226,
      273,
      267,
      283,
      362,
      185,
      315,
      403,
      348,
      245,
      382,
      330,
      347,
      385,
      428,
      148,
      300,
      339,
      198,
      335,
      424,
      371,
      412,
      361,
      312,
      368,
      432,
      308,
      364,
      72,
      205,
      329,
      423,
      473,
      522,
      543,
      302,
      427,
      528,
      417,
      419,
      203,
      352,
      442,
      304,
      451,
      355,
      488,
      376,
      359,
      581,
      554,
      494,
      525,
      415,
      464,
      530
    ]
  },
  "generateSaltUsingGET": {},
  "registerNewUserAccountUsingPOST": {},
  "getUserByIdUsingGET": {
    "id|path": [
      1,
      2,
      3,
      5
    ]
  },
  "updateUserUsingPUT": {
    "id|path": [
      1
    ]
  },
  "deleteByIdUsingDELETE": {
    "id|path": [
      4,
      2,
      5,
      3,
      8,
      6,
      7
    ]
  },
  "addRoleUsingPOST": {
    "id|path": [
      1,
      8
    ],
    "roleId|path": [
      1,
      3,
      8,
      9,
      13,
      5,
      16,
      2,
      46,
      30,
      23,
      58,
      27,
      38,
      40,
      61,
      70,
      77,
      64,
      50,
      90,
      78,
      115,
      104,
      107,
      150,
      108,
      133,
      111,
      69,
      105,
      158,
      123,
      144,
      124,
      139,
      147,
      163,
      52,
      140,
      233,
      193,
      279,
      242,
      264,
      294,
      319,
      342,
      360,
      336,
      332,
      222,
      347,
      198,
      415,
      406,
      178,
      432,
      447,
      412,
      182,
      72,
      343,
      317,
      303,
      308,
      497,
      256,
      100,
      543,
      451,
      413,
      404,
      312,
      547,
      359,
      488,
      548,
      528,
      167,
      271
    ]
  },
  "removeRoleUsingDELETE": {
    "id|path": [
      3,
      1,
      8
    ],
    "roleId|path": [
      1,
      10,
      2,
      5,
      18,
      6,
      9,
      17,
      20,
      16,
      8,
      13,
      3,
      30,
      46,
      23,
      27,
      38,
      48,
      40,
      58,
      64,
      81,
      43,
      68,
      66,
      70,
      55,
      79,
      73,
      110,
      86,
      123,
      112,
      111,
      113,
      78,
      77,
      91,
      90,
      61,
      89,
      87,
      115,
      147,
      36,
      139,
      134,
      117,
      149,
      108,
      107,
      180,
      169,
      163,
      100,
      168,
      104,
      50,
      192,
      233,
      158,
      213,
      193,
      206,
      200,
      39,
      295,
      256,
      281,
      332,
      230,
      264,
      249,
      255,
      239,
      228,
      232,
      315,
      330,
      124,
      282,
      224,
      254,
      309,
      381,
      182,
      105,
      329,
      348,
      391,
      356,
      69,
      229,
      148,
      372,
      385,
      243,
      156,
      144,
      380,
      279,
      364,
      280,
      140,
      320,
      321,
      462,
      312,
      479,
      342,
      294,
      402,
      487,
      460,
      178,
      287,
      514,
      150,
      360,
      133,
      259
    ]
  }
}